pyftc/LICENSE
pyftc/README.md
pyftc/__init__.py
pyftc/tests/__init__.py
pyftc/tests/acq_load.py
pyftc/tests/srs.py
pyftc/tests/data/test.rpc
pyftc-0.1.0.dist-info/METADATA
pyftc-0.1.0.dist-info/WHEEL
pyftc-0.1.0.dist-info/top_level.txt
pyftc-0.1.0.dist-info/RECORD
